mex/__init__.py
mex/common/__init__.py
mex/common/backend_api/__init__.py
mex/common/backend_api/connector.py
mex/common/cli.py
mex/common/connector/__init__.py
mex/common/connector/base.py
mex/common/connector/http.py
mex/common/connector/utils.py
mex/common/context.py
mex/common/exceptions.py
mex/common/extract.py
mex/common/fields.py
mex/common/identity/__init__.py
mex/common/identity/backend_api.py
mex/common/identity/base.py
mex/common/identity/memory.py
mex/common/identity/models.py
mex/common/identity/registry.py
mex/common/ldap/__init__.py
mex/common/ldap/connector.py
mex/common/ldap/extract.py
mex/common/ldap/models.py
mex/common/ldap/transform.py
mex/common/logging.py
mex/common/merged/__init__.py
mex/common/merged/main.py
mex/common/merged/types.py
mex/common/models/__init__.py
mex/common/models/access_platform.py
mex/common/models/activity.py
mex/common/models/base/__init__.py
mex/common/models/base/container.py
mex/common/models/base/extracted_data.py
mex/common/models/base/filter.py
mex/common/models/base/mapping.py
mex/common/models/base/merged_item.py
mex/common/models/base/model.py
mex/common/models/base/preview_item.py
mex/common/models/base/rules.py
mex/common/models/base/schema.py
mex/common/models/base/status.py
mex/common/models/bibliographic_resource.py
mex/common/models/consent.py
mex/common/models/contact_point.py
mex/common/models/distribution.py
mex/common/models/organization.py
mex/common/models/organizational_unit.py
mex/common/models/person.py
mex/common/models/primary_source.py
mex/common/models/resource.py
mex/common/models/variable.py
mex/common/models/variable_group.py
mex/common/orcid/__init__.py
mex/common/orcid/connector.py
mex/common/orcid/extract.py
mex/common/orcid/models.py
mex/common/orcid/transform.py
mex/common/organigram/__init__.py
mex/common/organigram/extract.py
mex/common/organigram/helpers.py
mex/common/organigram/models.py
mex/common/organigram/transform.py
mex/common/primary_source/__init__.py
mex_common-2.0.0.dist-info/METADATA
mex_common-2.0.0.dist-info/WHEEL
mex_common-2.0.0.dist-info/entry_points.txt
mex_common-2.0.0.dist-info/licenses/LICENSE
mex_common-2.0.0.dist-info/RECORD
