Metadata-Version: 2.1
Name: mex-common
Version: 2.0.0
Summary: Common library for MEx python projects.
Author-Email: MEx Team <mex@rki.de>
License: MIT License
Project-URL: Repository, https://github.com/robert-koch-institut/mex-common
Requires-Python: <3.12,>=3.11
Requires-Dist: backoff<3,>=2
Requires-Dist: click<9,>=8
Requires-Dist: langdetect<2,>=1
Requires-Dist: ldap3<3,>=2
Requires-Dist: mex-model<4.2,>=4.1.2
Requires-Dist: numpy<3,>=2
Requires-Dist: pandas<3,>=2
Requires-Dist: pyarrow<22,>=21
Requires-Dist: pydantic-settings<2.11,>=2
Requires-Dist: pydantic<2.10,>=2
Requires-Dist: pytz<2024.2,>=2024
Requires-Dist: requests<3,>=2
Provides-Extra: dev
Requires-Dist: ipdb>=0.13; extra == "dev"
Requires-Dist: mypy>=1; extra == "dev"
Requires-Dist: pandas-stubs; extra == "dev"
Requires-Dist: pytest-cov>=6; extra == "dev"
Requires-Dist: pytest-random-order>=1; extra == "dev"
Requires-Dist: pytest-xdist>=3; extra == "dev"
Requires-Dist: pytest>=8; extra == "dev"
Requires-Dist: ruff>=0.12; extra == "dev"
Requires-Dist: sphinx>=8; extra == "dev"
Requires-Dist: types-ldap3; extra == "dev"
Requires-Dist: types-pytz; extra == "dev"
Requires-Dist: types-requests; extra == "dev"
